django_async_stream/__init__.py
django_async_stream/_classes.py
django_async_stream-0.3.dist-info/WHEEL
django_async_stream-0.3.dist-info/METADATA
django_async_stream-0.3.dist-info/RECORD
