Metadata-Version: 2.1
Name: django-async-stream
Version: 0.3
Summary: Django extension that allow using asynchronous generators in StreamingHttpResponse
Home-page: https://github.com/svinerus/django-async-stream
License: UNKNOWN
Keywords: django, async, stream, streamhttp, streaminghttp, StreamingHttpResponse, ASGI, AsyncStreamingHttpResponse
Author: svinerus
Author-email: svinerus@gmail.com
Requires-Python: >=3.7
Requires-Dist: django
